jsonrpc/__init__.py
jsonrpc/__main__.py
jsonrpc/common.py
jsonrpc/example_server.py
jsonrpc/jsonutil.py
jsonrpc/proxy.py
jsonrpc/server.py
jsonrpc/twisted_proxy.py
jsonrpc/utilities.py
jsonrpc-3.0.1.dist-info/METADATA
jsonrpc-3.0.1.dist-info/WHEEL
jsonrpc-3.0.1.dist-info/top_level.txt
jsonrpc-3.0.1.dist-info/RECORD
