Metadata-Version: 2.1
Name: jsonrpc
Version: 3.0.1
Summary: A JSON-RPC 2.0 client-server library
Home-page: https://github.com/fiddlerwoaroof/jsonrpc
Author: Edward Langley
Author-email: langleyedward@gmail.com
License: BSD 2.0
Download-URL: https://github.com/fiddlerwoaroof/jsonrpc/tarball/master
Keywords: JSON,jsonrpc,rpc
Platform: UNKNOWN
Classifier: Development Status :: 4 - Beta
Classifier: Environment :: Web Environment
Classifier: Framework :: Twisted
Classifier: Intended Audience :: Developers
Classifier: License :: OSI Approved :: BSD License
Classifier: Operating System :: OS Independent
Classifier: Programming Language :: Python :: 3.8
Classifier: Topic :: Software Development :: Libraries :: Python Modules
Requires-Dist: pyOpenSSL
Requires-Dist: service-identity
Requires-Dist: Twisted
